README.rst
setup.cfg
setup.py
MetaMindApi.egg-info/PKG-INFO
MetaMindApi.egg-info/SOURCES.txt
MetaMindApi.egg-info/dependency_links.txt
MetaMindApi.egg-info/requires.txt
MetaMindApi.egg-info/top_level.txt
metamind/__init__.py
metamind/api/__init__.py
metamind/api/classification_data.py
metamind/api/classification_model.py
metamind/api/user.py
metamind/api/utils.py