Metadata-Version: 1.1
Name: MetaMindApi
Version: 1.2.2
Summary: MetaMind client for text and image classification
Home-page: https://www.metamind.io
Author: MetaMind Team
Author-email: contact@metamind.io
License: UNKNOWN
Keywords: metamind api
Platform: UNKNOWN
Classifier: Development Status :: 4 - Beta
Classifier: Intended Audience :: Developers
Classifier: Programming Language :: Python :: 2.7
Classifier: Natural Language :: English
Classifier: Operating System :: OS Independent
Classifier: Topic :: Scientific/Engineering :: Artificial Intelligence
